data_polyglot/__init__.py
data_polyglot/constants.py
data_polyglot/serializable.py
data_polyglot/table_data.py
data_polyglot/storage/local_storage.py
data_polyglot/storage/storage.py
data_polyglot-1.2.5.dist-info/METADATA
data_polyglot-1.2.5.dist-info/WHEEL
data_polyglot-1.2.5.dist-info/licenses/LICENSE
data_polyglot-1.2.5.dist-info/RECORD
