Metadata-Version: 2.1
Name: data_polyglot
Version: 1.2.5
Summary: Convenient way to model JSON payload and response with least lines of code to test API
Project-URL: Homepage, https://github.com/VH88/data_polyglot
Project-URL: Bug Tracker, https://github.com/VH88/data_polyglot/issues
Author-email: Vadim Harenco <vharenco@gmail.com>
License-Expression: Apache-2.0
License-File: LICENSE
Keywords: API,deserialize,json,payload,serialize,serializer,test automation,testing
Classifier: Intended Audience :: Developers
Classifier: Intended Audience :: Information Technology
Classifier: License :: OSI Approved :: Apache Software License
Classifier: Operating System :: MacOS
Classifier: Operating System :: Microsoft :: Windows
Classifier: Operating System :: POSIX
Classifier: Operating System :: Unix
Classifier: Programming Language :: Python :: 3.7
Classifier: Programming Language :: Python :: 3.8
Classifier: Programming Language :: Python :: 3.9
Classifier: Programming Language :: Python :: 3.10
Classifier: Programming Language :: Python :: 3.11
Requires-Python: >=3.7
